pyfaceit/__init__.py
pyfaceit/pyface.py
pyfaceit-1.0.2.dist-info/METADATA
pyfaceit-1.0.2.dist-info/WHEEL
pyfaceit-1.0.2.dist-info/top_level.txt
pyfaceit-1.0.2.dist-info/RECORD
