Metadata-Version: 2.1
Name: pyfaceit
Version: 1.0.2
Summary: Simple Package that allows the extraction of player data, this is a REST api and needs to be ran. This is a flask application
Home-page: UNKNOWN
Author: Milahn Martin
Author-email: <milahnmartin.develop@gmail.com>
License: UNKNOWN
Keywords: python,faceit,api,rest api,get data,flask
Platform: UNKNOWN
Classifier: Development Status :: 1 - Planning
Classifier: Intended Audience :: Developers
Classifier: Programming Language :: Python :: 3
Classifier: Operating System :: Unix
Classifier: Operating System :: MacOS :: MacOS X
Classifier: Operating System :: Microsoft :: Windows
Requires-Dist: requests
Requires-Dist: flask
Requires-Dist: bs4
